test_tool/__init__.py
test_tool/__main__.py
test_tool/base.py
test_tool/import_plugin.py
test_tool/substitute.py
test_tool/test_tool.py
test_tool/utils.py
test_tool_assert_plugin/__init__.py
test_tool_assert_plugin/__main__.py
test_tool_assert_plugin/main.py
test_tool_copy_files_ssh_plugin/__init__.py
test_tool_copy_files_ssh_plugin/__main__.py
test_tool_copy_files_ssh_plugin/main.py
test_tool_jdbc_sql_plugin/__init__.py
test_tool_jdbc_sql_plugin/__main__.py
test_tool_jdbc_sql_plugin/main.py
test_tool_python_plugin/__init__.py
test_tool_python_plugin/__main__.py
test_tool_python_plugin/main.py
test_tool_read_jar_manifest_plugin/__init__.py
test_tool_read_jar_manifest_plugin/__main__.py
test_tool_read_jar_manifest_plugin/main.py
test_tool_rest_plugin/__init__.py
test_tool_rest_plugin/__main__.py
test_tool_rest_plugin/main.py
test_tool_run_process_plugin/__init__.py
test_tool_run_process_plugin/__main__.py
test_tool_run_process_plugin/main.py
test_tool_secret_plugin/__init__.py
test_tool_secret_plugin/__main__.py
test_tool_secret_plugin/main.py
test_tool_selenium_plugin/__init__.py
test_tool_selenium_plugin/__main__.py
test_tool_selenium_plugin/actions.py
test_tool_selenium_plugin/main.py
test_tool_selenium_plugin/native.py
test_tool_sql_plus_plugin/__init__.py
test_tool_sql_plus_plugin/__main__.py
test_tool_sql_plus_plugin/main.py
test_tool_ssh_cmd_plugin/__init__.py
test_tool_ssh_cmd_plugin/__main__.py
test_tool_ssh_cmd_plugin/main.py
test_tool_suite_plugin/__init__.py
test_tool_suite_plugin/__main__.py
test_tool_suite_plugin/main.py
test_tool_timing_plugin/__init__.py
test_tool_timing_plugin/__main__.py
test_tool_timing_plugin/main.py
universal_test_tool-0.1.24.dist-info/LICENSE
universal_test_tool-0.1.24.dist-info/METADATA
universal_test_tool-0.1.24.dist-info/WHEEL
universal_test_tool-0.1.24.dist-info/entry_points.txt
universal_test_tool-0.1.24.dist-info/top_level.txt
universal_test_tool-0.1.24.dist-info/RECORD
