Metadata-Version: 2.1
Name: universal-test-tool
Version: 0.1.24
Summary: Awesome universal-test-tool to make tests configurable with a yaml file.
Home-page: https://github.com/jackovsky8/universal-test-tool/
Author: jackovsky8
Requires-Python: >=3.9
License-File: LICENSE
Requires-Dist: types-PyYAML
Requires-Dist: python-dotenv
Requires-Dist: paramiko
Requires-Dist: types-paramiko
Requires-Dist: JayDeBeApi
Requires-Dist: requests
Requires-Dist: types-requests
Requires-Dist: selenium
Requires-Dist: webdriver-manager
Requires-Dist: pyyaml
Requires-Dist: keyring <25.0.0
Requires-Dist: keyring-pybridge >=0.4.0
Requires-Dist: xmltodict >=0.13.0
Requires-Dist: types-xmltodict
Provides-Extra: test
Requires-Dist: pytest ; extra == 'test'
Requires-Dist: coverage ; extra == 'test'
Requires-Dist: flake8 ; extra == 'test'
Requires-Dist: black ; extra == 'test'
Requires-Dist: isort ; extra == 'test'
Requires-Dist: pytest-cov ; extra == 'test'
Requires-Dist: mypy ; extra == 'test'
Requires-Dist: gitchangelog ; extra == 'test'
Requires-Dist: mkdocs ; extra == 'test'
Requires-Dist: mkdocs-material ; extra == 'test'
Requires-Dist: testcontainers ; extra == 'test'
Requires-Dist: setuptools ; extra == 'test'
Requires-Dist: types-setuptools ; extra == 'test'
Requires-Dist: mock ; extra == 'test'
